movie_colorbar/__init__.py
movie_colorbar/__main__.py
movie_colorbar/bar.py
movie_colorbar/colors.py
movie_colorbar/constants.py
movie_colorbar/extract.py
movie_colorbar/image.py
movie_colorbar/jit.py
movie_colorbar/process.py
movie_colorbar-0.3.0.dist-info/METADATA
movie_colorbar-0.3.0.dist-info/WHEEL
movie_colorbar-0.3.0.dist-info/entry_points.txt
movie_colorbar-0.3.0.dist-info/licenses/LICENSE
movie_colorbar-0.3.0.dist-info/RECORD
