Metadata-Version: 2.4
Name: movie_colorbar
Version: 0.3.0
Summary: Turn a video into a colorbar
Project-URL: homepage, https://github.com/fsoubelet/Movie_Colorbar
Project-URL: repository, https://github.com/fsoubelet/Movie_Colorbar
Author-email: Felix Soubelet <felix.soubelet@github.com>
License-Expression: MIT
License-File: LICENSE
Classifier: Development Status :: 4 - Beta
Classifier: License :: OSI Approved :: MIT License
Classifier: Natural Language :: English
Classifier: Programming Language :: Python
Classifier: Programming Language :: Python :: 3 :: Only
Classifier: Programming Language :: Python :: 3.10
Classifier: Programming Language :: Python :: 3.11
Classifier: Programming Language :: Python :: 3.12
Classifier: Programming Language :: Python :: 3.13
Classifier: Programming Language :: Python :: Implementation :: CPython
Classifier: Topic :: Utilities
Requires-Python: >=3.10
Requires-Dist: loguru<1.0
Requires-Dist: pillow>=10.0
Requires-Dist: typer>=0.10
Provides-Extra: fast
Requires-Dist: joblib>=1.4; extra == 'fast'
Requires-Dist: numba>=0.60.0; extra == 'fast'
